petercat_utils/README.md
petercat_utils/__init__.py
petercat_utils/data_class.py
petercat_utils/db/client/supabase.py
petercat_utils/rag_helper/git_doc_task.py
petercat_utils/rag_helper/git_issue_task.py
petercat_utils/rag_helper/git_task.py
petercat_utils/rag_helper/github_file_loader.py
petercat_utils/rag_helper/issue_retrieval.py
petercat_utils/rag_helper/retrieval.py
petercat_utils/rag_helper/task.py
petercat_utils/utils/env.py
petercat_utils-0.1.42.dist-info/LICENSE
petercat_utils-0.1.42.dist-info/METADATA
petercat_utils-0.1.42.dist-info/WHEEL
petercat_utils-0.1.42.dist-info/RECORD
