Metadata-Version: 2.3
Name: petercat_utils
Version: 0.1.42
Summary: 
Author: raoha.rh
Author-email: raohai.rh@antgroup.com
Requires-Python: >=3.9,<4.0
Classifier: Programming Language :: Python :: 3
Classifier: Programming Language :: Python :: 3.9
Classifier: Programming Language :: Python :: 3.10
Classifier: Programming Language :: Python :: 3.11
Classifier: Programming Language :: Python :: 3.12
Classifier: Programming Language :: Python :: 3.13
Requires-Dist: PyGithub (==2.3.0)
Requires-Dist: langchain (>=0.3,<0.4)
Requires-Dist: langchain_community (>=0.3,<0.4)
Requires-Dist: langchain_core (>=0.3,<0.4)
Requires-Dist: langchain_openai (==0.3.3)
Requires-Dist: pydantic (>=2.7.0,<3)
Requires-Dist: python-dotenv (==1.0.0)
Requires-Dist: supabase (==2.6.0)
